django_loggable_util/__init__.py
django_loggable_util/config.py
django_loggable_util/loggable.py
django_loggable_util-0.0.4.dist-info/LICENSE.txt
django_loggable_util-0.0.4.dist-info/METADATA
django_loggable_util-0.0.4.dist-info/WHEEL
django_loggable_util-0.0.4.dist-info/top_level.txt
django_loggable_util-0.0.4.dist-info/RECORD
