Metadata-Version: 2.1
Name: django-loggable-util
Version: 0.0.4
Summary: Separate logging from class based view business code
Home-page: https://github.com/Ruhshan/django-loggable-util
Author: Ruhshan Ahmed Abir
Author-email: ruhshan.ahmed@gmail.com
License: MIT
Keywords: Django,Loggable,Wrapper,Generic view,Class based view
Platform: UNKNOWN
Classifier: Development Status :: 3 - Alpha
Classifier: Intended Audience :: Developers
Classifier: Topic :: Software Development :: Libraries
Classifier: License :: OSI Approved :: MIT License
Classifier: Framework :: Django
Classifier: Programming Language :: Python :: 3
Classifier: Programming Language :: Python :: 3.4
Classifier: Programming Language :: Python :: 3.5
Classifier: Programming Language :: Python :: 3.6
Classifier: Programming Language :: Python :: 3.7
